fast_legion/__init__.py
fast_legion/constants.py
fast_legion/main.py
fast_legion/schemas/__init__.py
fast_legion/schemas/token.py
fast_legion/security_utils.py
fast_legion-0.1.0.dist-info/LICENSE
fast_legion-0.1.0.dist-info/WHEEL
fast_legion-0.1.0.dist-info/METADATA
fast_legion-0.1.0.dist-info/RECORD
